README.rst
setup.py
WQ_SDK.egg-info/PKG-INFO
WQ_SDK.egg-info/SOURCES.txt
WQ_SDK.egg-info/dependency_links.txt
WQ_SDK.egg-info/top_level.txt
wq/__init__.py
wq/utils.py